cd_http/__init__.py
cd_http/http.py
cd_http/version.py
cd_http-0.2.4.dist-info/LICENSE.md
cd_http-0.2.4.dist-info/LICENSE.txt
cd_http-0.2.4.dist-info/METADATA
cd_http-0.2.4.dist-info/WHEEL
cd_http-0.2.4.dist-info/RECORD
