Metadata-Version: 2.1
Name: cd-http
Version: 0.2.4
Summary: An HTTP wrapper around the wonderful requests library to make it easier for new users and old.
License: MIT
Author: Nick Capasso
Author-email: codedocta@gmail.com
Requires-Python: >=3.9,<4.0
Classifier: License :: OSI Approved :: MIT License
Classifier: Programming Language :: Python :: 3
Classifier: Programming Language :: Python :: 3.9
Classifier: Programming Language :: Python :: 3.10
Classifier: Programming Language :: Python :: 3.11
Classifier: Programming Language :: Python :: 3.12
Requires-Dist: cd_proxy_manager (>=0.2.5,<0.3.0)
Requires-Dist: fake-useragent (>=1.5.1,<2.0.0)
Requires-Dist: requests (>=2.32.3,<3.0.0)
